{
  "ok": true,
  "provider": {
    "quote": "tencent-finance",
    "fx": "frankfurter",
    "dividend": "yfinance",
    "dividendVerify": "disabled"
  },
  "updatedAt": "2026-04-28T12:01:42.484667Z",
  "rates": {
    "CNY": 1,
    "USD": 6.8231,
    "HKD": 0.8706
  },
  "quotes": {
    "00700.HK": {
      "symbol": "00700.HK",
      "name": "腾讯控股",
      "market": "HK",
      "currency": "HKD",
      "price": 473.8,
      "previousClose": 478.6,
      "dividendPerShareTtm": 4.5,
      "dividendSource": "yfinance",
      "dividendUpdatedAt": "2026-04-28T12:01:34.080800Z",
      "lastExDate": "2025-05-15",
      "dividendStatus": "fresh"
    },
    "600519.SH": {
      "symbol": "600519.SH",
      "name": "贵州茅台",
      "market": "CN",
      "currency": "CNY",
      "price": 1405.0,
      "previousClose": 1403.2,
      "dividendPerShareTtm": 51.63,
      "dividendSource": "yfinance",
      "dividendUpdatedAt": "2026-04-28T12:01:34.363959Z",
      "lastExDate": "2025-12-18",
      "dividendStatus": "fresh"
    },
    "000651.SZ": {
      "symbol": "000651.SZ",
      "name": "格力电器",
      "market": "CN",
      "currency": "CNY",
      "price": 38.44,
      "previousClose": 37.51,
      "dividendPerShareTtm": 4.0,
      "dividendSource": "yfinance",
      "dividendUpdatedAt": "2026-04-28T12:01:34.668083Z",
      "lastExDate": "2026-01-22",
      "dividendStatus": "fresh"
    },
    "00883.HK": {
      "symbol": "00883.HK",
      "name": "中国海洋石油",
      "market": "HK",
      "currency": "HKD",
      "price": 28.98,
      "previousClose": 28.44,
      "dividendPerShareTtm": 1.39,
      "dividendSource": "yfinance",
      "dividendUpdatedAt": "2026-04-28T12:01:34.983296Z",
      "lastExDate": "2025-09-10",
      "dividendStatus": "fresh"
    },
    "06049.HK": {
      "symbol": "06049.HK",
      "name": "保利物业",
      "market": "HK",
      "currency": "HKD",
      "price": 30.84,
      "previousClose": 30.84,
      "dividendPerShareTtm": 1.45332,
      "dividendSource": "yfinance",
      "dividendUpdatedAt": "2026-04-28T12:01:35.270876Z",
      "lastExDate": "2025-06-09",
      "dividendStatus": "fresh"
    },
    "000333.SZ": {
      "symbol": "000333.SZ",
      "name": "美的集团",
      "market": "CN",
      "currency": "CNY",
      "price": 80.45,
      "previousClose": 79.5,
      "dividendPerShareTtm": 4.0,
      "dividendSource": "yfinance",
      "dividendUpdatedAt": "2026-04-28T12:01:35.575748Z",
      "lastExDate": "2025-11-17",
      "dividendStatus": "fresh"
    },
    "02669.HK": {
      "symbol": "02669.HK",
      "name": "中海物业",
      "market": "HK",
      "currency": "HKD",
      "price": 3.95,
      "previousClose": 3.97,
      "dividendPerShareTtm": 0.195,
      "dividendSource": "yfinance",
      "dividendUpdatedAt": "2026-04-28T12:01:35.853112Z",
      "lastExDate": "2025-09-18",
      "dividendStatus": "fresh"
    },
    "PDD": {
      "symbol": "PDD",
      "name": "拼多多",
      "market": "US",
      "currency": "USD",
      "price": 98.47,
      "previousClose": 98.03,
      "dividendPerShareTtm": 0.0,
      "dividendSource": "yfinance",
      "dividendUpdatedAt": "2026-04-28T12:01:36.113236Z",
      "lastExDate": "",
      "dividendStatus": "missing"
    },
    "01571.HK": {
      "symbol": "01571.HK",
      "name": "信邦控股",
      "market": "HK",
      "currency": "HKD",
      "price": 4.3,
      "previousClose": 4.42,
      "dividendPerShareTtm": 0.5,
      "dividendSource": "yfinance",
      "dividendUpdatedAt": "2026-04-28T12:01:36.329888Z",
      "lastExDate": "2025-09-24",
      "dividendStatus": "fresh"
    },
    "00270.HK": {
      "symbol": "00270.HK",
      "name": "粤海投资",
      "market": "HK",
      "currency": "HKD",
      "price": 8.15,
      "previousClose": 8.13,
      "dividendPerShareTtm": 0.3393,
      "dividendSource": "yfinance",
      "dividendUpdatedAt": "2026-04-28T12:01:36.718218Z",
      "lastExDate": "2025-10-07",
      "dividendStatus": "fresh"
    },
    "09618.HK": {
      "symbol": "09618.HK",
      "name": "京东集团-SW",
      "market": "HK",
      "currency": "HKD",
      "price": 115.3,
      "previousClose": 117.0,
      "dividendPerShareTtm": 3.918045,
      "dividendSource": "yfinance",
      "dividendUpdatedAt": "2026-04-28T12:01:36.963622Z",
      "lastExDate": "2026-04-07",
      "dividendStatus": "fresh"
    },
    "00728.HK": {
      "symbol": "00728.HK",
      "name": "中国电信",
      "market": "HK",
      "currency": "HKD",
      "price": 5.17,
      "previousClose": 5.14,
      "dividendPerShareTtm": 0.299901,
      "dividendSource": "yfinance",
      "dividendUpdatedAt": "2026-04-28T12:01:37.271100Z",
      "lastExDate": "2025-08-26",
      "dividendStatus": "fresh"
    },
    "02333.HK": {
      "symbol": "02333.HK",
      "name": "长城汽车",
      "market": "HK",
      "currency": "HKD",
      "price": 11.88,
      "previousClose": 12.45,
      "dividendPerShareTtm": 0.49233,
      "dividendSource": "yfinance",
      "dividendUpdatedAt": "2026-04-28T12:01:37.593604Z",
      "lastExDate": "2025-07-07",
      "dividendStatus": "fresh"
    },
    "600177.SH": {
      "symbol": "600177.SH",
      "name": "雅戈尔",
      "market": "CN",
      "currency": "CNY",
      "price": 7.45,
      "previousClose": 7.64,
      "dividendPerShareTtm": 0.44,
      "dividendSource": "yfinance",
      "dividendUpdatedAt": "2026-04-28T12:01:37.850899Z",
      "lastExDate": "2026-03-26",
      "dividendStatus": "fresh"
    },
    "03900.HK": {
      "symbol": "03900.HK",
      "name": "绿城中国",
      "market": "HK",
      "currency": "HKD",
      "price": 9.09,
      "previousClose": 9.06,
      "dividendPerShareTtm": 0.328,
      "dividendSource": "yfinance",
      "dividendUpdatedAt": "2026-04-28T12:01:38.137353Z",
      "lastExDate": "2025-06-24",
      "dividendStatus": "fresh"
    },
    "01995.HK": {
      "symbol": "01995.HK",
      "name": "永升服务",
      "market": "HK",
      "currency": "HKD",
      "price": 1.91,
      "previousClose": 1.94,
      "dividendPerShareTtm": 0.1617,
      "dividendSource": "yfinance",
      "dividendUpdatedAt": "2026-04-28T12:01:38.349176Z",
      "lastExDate": "2025-09-01",
      "dividendStatus": "fresh"
    },
    "03316.HK": {
      "symbol": "03316.HK",
      "name": "滨江服务",
      "market": "HK",
      "currency": "HKD",
      "price": 23.46,
      "previousClose": 23.5,
      "dividendPerShareTtm": 1.702,
      "dividendSource": "yfinance",
      "dividendUpdatedAt": "2026-04-28T12:01:38.629711Z",
      "lastExDate": "2025-09-02",
      "dividendStatus": "fresh"
    },
    "00816.HK": {
      "symbol": "00816.HK",
      "name": "金茂服务",
      "market": "HK",
      "currency": "HKD",
      "price": 2.5,
      "previousClose": 2.52,
      "dividendPerShareTtm": 0.249,
      "dividendSource": "yfinance",
      "dividendUpdatedAt": "2026-04-28T12:01:38.893643Z",
      "lastExDate": "2025-09-07",
      "dividendStatus": "fresh"
    },
    "513530.SH": {
      "symbol": "513530.SH",
      "name": "港股通红利ETF华泰柏瑞",
      "market": "CN",
      "currency": "CNY",
      "price": 1.669,
      "previousClose": 1.668,
      "dividendPerShareTtm": 0.13,
      "dividendSource": "yfinance",
      "dividendUpdatedAt": "2026-04-28T12:01:39.179959Z",
      "lastExDate": "2026-04-19",
      "dividendStatus": "fresh"
    },
    "00823.HK": {
      "symbol": "00823.HK",
      "name": "领展房产基金",
      "market": "HK",
      "currency": "HKD",
      "price": 38.96,
      "previousClose": 38.88,
      "dividendPerShareTtm": 2.6433,
      "dividendSource": "yfinance",
      "dividendUpdatedAt": "2026-04-28T12:01:39.526343Z",
      "lastExDate": "2025-12-01",
      "dividendStatus": "fresh"
    },
    "02156.HK": {
      "symbol": "02156.HK",
      "name": "建发物业",
      "market": "HK",
      "currency": "HKD",
      "price": 2.9,
      "previousClose": 2.92,
      "dividendPerShareTtm": 0.15,
      "dividendSource": "yfinance",
      "dividendUpdatedAt": "2026-04-28T12:01:39.754584Z",
      "lastExDate": "2025-05-26",
      "dividendStatus": "fresh"
    },
    "601088.SH": {
      "symbol": "601088.SH",
      "name": "中国神华",
      "market": "CN",
      "currency": "CNY",
      "price": 48.15,
      "previousClose": 46.78,
      "dividendPerShareTtm": 3.24,
      "dividendSource": "yfinance",
      "dividendUpdatedAt": "2026-04-28T12:01:40.045219Z",
      "lastExDate": "2025-11-09",
      "dividendStatus": "fresh"
    },
    "00941.HK": {
      "symbol": "00941.HK",
      "name": "中国移动",
      "market": "HK",
      "currency": "HKD",
      "price": 84.65,
      "previousClose": 84.4,
      "dividendPerShareTtm": 5.24,
      "dividendSource": "yfinance",
      "dividendUpdatedAt": "2026-04-28T12:01:40.303456Z",
      "lastExDate": "2025-08-31",
      "dividendStatus": "fresh"
    },
    "01088.HK": {
      "symbol": "01088.HK",
      "name": "中国神华",
      "market": "HK",
      "currency": "HKD",
      "price": 48.2,
      "previousClose": 47.26,
      "dividendPerShareTtm": 3.5226,
      "dividendSource": "yfinance",
      "dividendUpdatedAt": "2026-04-28T12:01:40.628087Z",
      "lastExDate": "2025-10-29",
      "dividendStatus": "fresh"
    },
    "01836.HK": {
      "symbol": "01836.HK",
      "name": "九兴控股",
      "market": "HK",
      "currency": "HKD",
      "price": 15.06,
      "previousClose": 15.05,
      "dividendPerShareTtm": 1.58,
      "dividendSource": "yfinance",
      "dividendUpdatedAt": "2026-04-28T12:01:40.910430Z",
      "lastExDate": "2025-09-02",
      "dividendStatus": "fresh"
    },
    "01023.HK": {
      "symbol": "01023.HK",
      "name": "时代集团控股",
      "market": "HK",
      "currency": "HKD",
      "price": 0.495,
      "previousClose": 0.495,
      "dividendPerShareTtm": 0.06,
      "dividendSource": "yfinance",
      "dividendUpdatedAt": "2026-04-28T12:01:41.156262Z",
      "lastExDate": "2026-03-25",
      "dividendStatus": "fresh"
    }
  }
}